setup.py
hearts/__init__.py
hearts/axis.py
hearts/bars.py
hearts/chart.py
hearts/datatype.py
hearts/dots.py
hearts/grid.py
hearts/line.py
hearts/linear.py
hearts/ordinal.py
hearts/scale.py
hearts/scoreticker.py
hearts/scoretimeticker.py
hearts/series.py
hearts/svg.py
hearts/temporal.py
hearts/theme.py
hearts/ticker.py
hearts/utils.py
hearts.egg-info/PKG-INFO
hearts.egg-info/SOURCES.txt
hearts.egg-info/dependency_links.txt
hearts.egg-info/entry_points.txt
hearts.egg-info/top_level.txt