Metadata-Version: 1.1
Name: hearts
Version: 0.0.0
Summary: A simple charting library. Derived from https://github.com/wireservice/leather.
Home-page: https://github.com/gwk/hearts
Author: George King
Author-email: george.w.king@gmail.com
License: MIT
Platform: UNKNOWN
Classifier: Development Status :: 3 - Alpha
Classifier: Environment :: Console
Classifier: Intended Audience :: Developers
Classifier: License :: CC0 1.0 Universal (CC0 1.0) Public Domain Dedication
Classifier: Programming Language :: Python :: 3 :: Only
